utsc/scripts/__init__.py
utsc/scripts/__main__.py
utsc/scripts/aruba.py
utsc/scripts/bluecat.py
utsc_scripts-2022.5.26.dist-info/METADATA
utsc_scripts-2022.5.26.dist-info/WHEEL
utsc_scripts-2022.5.26.dist-info/entry_points.txt
utsc_scripts-2022.5.26.dist-info/RECORD
