Metadata-Version: 2.1
Name: utsc-scripts
Version: 2022.5.26
Summary: a collection of scripts and one-off tools
Author-email: Alex Tremblay <alex.tremblay@utoronto.ca>, University of Toronto Governing Council <governing.council@utoronto.ca>
Requires-Python: >=3.10
Requires-Dist: ldap3
Requires-Dist: prompt-toolkit>=3.0.19
Requires-Dist: pydantic>=1.9.0
Requires-Dist: pyquery>=1.4.0
Requires-Dist: rich>=10.7.0
Requires-Dist: utsc-core
